tests/__init__.py
tests/context.py
tests/test.py
tests/test_userpass.py
userpass/__init__.py
userpass/userpass.py
userpass-0.1.1.dist-info/DESCRIPTION.rst
userpass-0.1.1.dist-info/METADATA
userpass-0.1.1.dist-info/RECORD
userpass-0.1.1.dist-info/WHEEL
userpass-0.1.1.dist-info/metadata.json
userpass-0.1.1.dist-info/top_level.txt
