Metadata-Version: 2.0
Name: userpass
Version: 0.1.1
Summary: Store username and password at $HOME
Home-page: https://github.com/zYeoman/userpass
Author: Yongwen Zhuang
Author-email: zyeoman@163.com
Maintainer: Yongwen Zhuang
Maintainer-email: zyeoman@163.com
License: MIT
Keywords: password,store
Platform: UNKNOWN
Classifier: Development Status :: 4 - Beta
Classifier: Intended Audience :: Developers
Classifier: License :: OSI Approved :: MIT License
Classifier: Natural Language :: English
Classifier: Operating System :: OS Independent
Classifier: Programming Language :: Python :: 2.7
Classifier: Programming Language :: Python :: 3.5
Classifier: Programming Language :: Python :: 3.6
Classifier: Programming Language :: Python :: Implementation :: CPython
Classifier: Programming Language :: Python :: Implementation :: PyPy
